aliyunsdkbssopenapi/__init__.py
aliyunsdkbssopenapi/endpoint.py
aliyunsdkbssopenapi/request/__init__.py
aliyunsdkbssopenapi/request/v20171214/AddAccountRelationRequest.py
aliyunsdkbssopenapi/request/v20171214/AllocateCostUnitResourceRequest.py
aliyunsdkbssopenapi/request/v20171214/ApplyInvoiceRequest.py
aliyunsdkbssopenapi/request/v20171214/CancelOrderRequest.py
aliyunsdkbssopenapi/request/v20171214/ChangeResellerConsumeAmountRequest.py
aliyunsdkbssopenapi/request/v20171214/ConfirmRelationRequest.py
aliyunsdkbssopenapi/request/v20171214/ConvertChargeTypeRequest.py
aliyunsdkbssopenapi/request/v20171214/CreateAgAccountRequest.py
aliyunsdkbssopenapi/request/v20171214/CreateCostUnitRequest.py
aliyunsdkbssopenapi/request/v20171214/CreateInstanceRequest.py
aliyunsdkbssopenapi/request/v20171214/CreateResellerUserQuotaRequest.py
aliyunsdkbssopenapi/request/v20171214/CreateResourcePackageRequest.py
aliyunsdkbssopenapi/request/v20171214/CreateSavingsPlansInstanceRequest.py
aliyunsdkbssopenapi/request/v20171214/DeleteCostUnitRequest.py
aliyunsdkbssopenapi/request/v20171214/DescribeInstanceBillRequest.py
aliyunsdkbssopenapi/request/v20171214/DescribePricingModuleRequest.py
aliyunsdkbssopenapi/request/v20171214/DescribeResourceCoverageDetailRequest.py
aliyunsdkbssopenapi/request/v20171214/DescribeResourceCoverageTotalRequest.py
aliyunsdkbssopenapi/request/v20171214/DescribeResourcePackageProductRequest.py
aliyunsdkbssopenapi/request/v20171214/DescribeResourceUsageDetailRequest.py
aliyunsdkbssopenapi/request/v20171214/DescribeResourceUsageTotalRequest.py
aliyunsdkbssopenapi/request/v20171214/DescribeSavingsPlansCoverageDetailRequest.py
aliyunsdkbssopenapi/request/v20171214/DescribeSavingsPlansCoverageTotalRequest.py
aliyunsdkbssopenapi/request/v20171214/DescribeSavingsPlansUsageDetailRequest.py
aliyunsdkbssopenapi/request/v20171214/DescribeSavingsPlansUsageTotalRequest.py
aliyunsdkbssopenapi/request/v20171214/DescribeSplitItemBillRequest.py
aliyun_python_sdk_bssopenapi-2.0.3.dist-info/LICENSE
aliyun_python_sdk_bssopenapi-2.0.3.dist-info/METADATA
aliyun_python_sdk_bssopenapi-2.0.3.dist-info/WHEEL
aliyun_python_sdk_bssopenapi-2.0.3.dist-info/top_level.txt
aliyun_python_sdk_bssopenapi-2.0.3.dist-info/RECORD
